pagesmith/__about__.py
pagesmith/__init__.py
pagesmith/chapter_detector.py
pagesmith/html_page_splitter.py
pagesmith/page_splitter.py
pagesmith/parser.py
pagesmith/refine_html.py
pagesmith/refine_html_beautiful_soup.py
pagesmith-2.1.1.dist-info/METADATA
pagesmith-2.1.1.dist-info/WHEEL
pagesmith-2.1.1.dist-info/licenses/LICENSE.txt
pagesmith-2.1.1.dist-info/RECORD
