Metadata-Version: 2.4
Name: pagesmith
Version: 2.1.1
Summary: HTML page splitter (preserves tags), text page splitter (natural breaks), and chapter detector for pure text.
Project-URL: Homepage, https://andgineer.github.io/pagesmith/
Project-URL: Documentation, https://andgineer.github.io/pagesmith/
Author-email: Andrey Sorokin <andrey@sorokin.engineer>
License: Copyright (c) 2024 Andrey Sorokin <andrey@sorokin.engineer>
License-File: LICENSE.txt
Keywords: one,two
Classifier: License :: OSI Approved :: MIT License
Classifier: Operating System :: OS Independent
Classifier: Programming Language :: Python :: 3
Requires-Python: >=3.10
Requires-Dist: lxml
